mothership_cli/__init__.py
mothership_cli/cli.py
mothership_cli-1.1.8.dist-info/licenses/LICENSE
mothership_cli-1.1.8.dist-info/METADATA
mothership_cli-1.1.8.dist-info/WHEEL
mothership_cli-1.1.8.dist-info/entry_points.txt
mothership_cli-1.1.8.dist-info/top_level.txt
mothership_cli-1.1.8.dist-info/RECORD
