Metadata-Version: 2.4
Name: mothership-cli
Version: 1.1.8
Summary: Modular Python project scaffolding CLI for rapid startup and deployment
Author: Nikolai Janiszewsky
Classifier: Programming Language :: Python :: 3
Classifier: License :: OSI Approved :: MIT License
Classifier: Operating System :: OS Independent
License-File: LICENSE
Dynamic: author
Dynamic: classifier
Dynamic: description
Dynamic: description-content-type
Dynamic: license-file
Dynamic: summary
